medialog.iconpicker-0.6.1-py2.7-nspkg.pth
medialog/iconpicker/__init__.py
medialog/iconpicker/behavior.py
medialog/iconpicker/behaviors.zcml
medialog/iconpicker/configure.zcml
medialog/iconpicker/interfaces.py
medialog/iconpicker/tests.py
medialog/iconpicker/views.py
medialog/iconpicker/browser/__init__.py
medialog/iconpicker/browser/configure.zcml
medialog/iconpicker/browser/icontile.pt
medialog/iconpicker/browser/multiicontile.pt
medialog/iconpicker/browser/tiles.py
medialog/iconpicker/locales/README.txt
medialog/iconpicker/profiles/default/metadata.xml
medialog/iconpicker/profiles/default/registry.xml
medialog/iconpicker/resources/bootstrap.min.js
medialog/iconpicker/resources/jquery-1.10.2.min.js
medialog/iconpicker/resources/jscolor.js
medialog/iconpicker/resources/jscolor.min.js
medialog/iconpicker/resources/bootstrap-3.2.0/css/bootstrap-theme.css
medialog/iconpicker/resources/bootstrap-3.2.0/css/bootstrap-theme.css.map
medialog/iconpicker/resources/bootstrap-3.2.0/css/bootstrap-theme.min.css
medialog/iconpicker/resources/bootstrap-3.2.0/css/bootstrap.css
medialog/iconpicker/resources/bootstrap-3.2.0/css/bootstrap.css.map
medialog/iconpicker/resources/bootstrap-3.2.0/css/bootstrap.min.css
medialog/iconpicker/resources/bootstrap-3.2.0/css/docs.css
medialog/iconpicker/resources/bootstrap-3.2.0/css/pygments-manni.css
medialog/iconpicker/resources/bootstrap-3.2.0/fonts/glyphicons-halflings-regular.eot
medialog/iconpicker/resources/bootstrap-3.2.0/fonts/glyphicons-halflings-regular.svg
medialog/iconpicker/resources/bootstrap-3.2.0/fonts/glyphicons-halflings-regular.ttf
medialog/iconpicker/resources/bootstrap-3.2.0/fonts/glyphicons-halflings-regular.woff
medialog/iconpicker/resources/bootstrap-3.2.0/js/bootstrap.js
medialog/iconpicker/resources/bootstrap-3.2.0/js/bootstrap.min.js
medialog/iconpicker/resources/bootstrap-iconpicker/css/bootstrap-iconpicker.css
medialog.iconpicker-0.6.1.dist-info/DESCRIPTION.rst
medialog.iconpicker-0.6.1.dist-info/METADATA
medialog.iconpicker-0.6.1.dist-info/RECORD
medialog.iconpicker-0.6.1.dist-info/WHEEL
medialog.iconpicker-0.6.1.dist-info/entry_points.txt
medialog.iconpicker-0.6.1.dist-info/metadata.json
medialog.iconpicker-0.6.1.dist-info/namespace_packages.txt
medialog.iconpicker-0.6.1.dist-info/top_level.txt
