Metadata-Version: 2.0
Name: medialog.iconpicker
Version: 0.6.1
Summary: iconpicker for Plone
Home-page: http://github.com/espenmn/medialog.iconpicker
Author: Espen Moe-Nilssen
Author-email: espen@medialog.no
License: GPL
Platform: UNKNOWN
Classifier: Framework :: Plone
Classifier: Programming Language :: Python
Classifier: Topic :: Software Development :: Libraries :: Python Modules
Requires-Dist: setuptools
Requires-Dist: plone.app.dexterity
Requires-Dist: plone.behavior
Requires-Dist: plone.directives.form
Requires-Dist: collective.js.bootstrap
Requires-Dist: medialog.controlpanel
Requires-Dist: plone.api
Requires-Dist: collective.z3cform.datagridfield
Requires-Dist: lineage.registry
